falsa-0.0.6.dist-info/METADATA
falsa-0.0.6.dist-info/WHEEL
falsa-0.0.6.dist-info/entry_points.txt
falsa/__init__.py
falsa/app.py
falsa/local_fs.py
falsa/native.cpython-312-aarch64-linux-gnu.so
falsa/utils.py
falsa-0.0.6.dist-info/RECORD
