Metadata-Version: 2.4
Name: falsa
Version: 0.0.6
Classifier: Programming Language :: Rust
Classifier: Programming Language :: Python :: Implementation :: CPython
Classifier: Programming Language :: Python :: Implementation :: PyPy
Requires-Dist: pyarrow
Requires-Dist: typer
Requires-Dist: numpy
Requires-Dist: ruff ; extra == 'dev'
Requires-Dist: ipython ; extra == 'dev'
Provides-Extra: dev
Summary: Unofficial Rust-based implementation of H2O benchmark dataset generation
Maintainer-email: Sem <ssinchenko@apache.org>
License-Expression: Apache 2.0
Requires-Python: >=3.9
